[
  {
    "id": "b-1771692725121",
    "timestamp": "2026-02-21T16:52:05.121Z",
    "duration": 0,
    "status": "failed",
    "backend": "OSS",
    "device": "LFE5U-85F-6BG381C",
    "stages": [
      "synth",
      "pnr",
      "pack"
    ],
    "warnings": 0,
    "errors": 1
  },
  {
    "id": "b-1771692798113",
    "timestamp": "2026-02-21T16:53:18.113Z",
    "duration": 2,
    "status": "failed",
    "backend": "OSS",
    "device": "LFE5U-85F-6BG381C",
    "stages": [
      "synth",
      "pnr",
      "pack"
    ],
    "warnings": 0,
    "errors": 1
  },
  {
    "id": "b-1771693375009",
    "timestamp": "2026-02-21T17:02:55.009Z",
    "duration": 5,
    "status": "success",
    "backend": "OSS",
    "device": "LFE5U-85F-6BG381C",
    "stages": [
      "synth",
      "pnr",
      "pack"
    ],
    "warnings": 0,
    "errors": 0,
    "fmaxMhz": 206.4,
    "ffUsed": 33,
    "ffTotal": 83640
  },
  {
    "id": "b-1771694512093",
    "timestamp": "2026-02-21T17:21:52.093Z",
    "duration": 3,
    "status": "success",
    "backend": "OSS",
    "device": "LFE5U-85F-6BG381C",
    "stages": [
      "synth",
      "pnr",
      "pack"
    ],
    "warnings": 0,
    "errors": 0,
    "fmaxMhz": 206.4,
    "ffUsed": 33,
    "ffTotal": 83640
  },
  {
    "id": "b-1771695534553",
    "timestamp": "2026-02-21T17:38:54.553Z",
    "duration": 2,
    "status": "success",
    "backend": "OSS",
    "device": "LFE5U-85F-6BG381C",
    "stages": [
      "synth",
      "pnr",
      "pack"
    ],
    "warnings": 0,
    "errors": 0,
    "commitHash": "e17e16f",
    "commitMsg": "Pre-build: LED Blinker 2026-02-21",
    "fmaxMhz": 206.4,
    "ffUsed": 33,
    "ffTotal": 83640
  }
]